{
  "accentColor": "{{appsmith.theme.colors.primaryColor}}",
  "animateLoading": true,
  "borderColor": "#E0DEDE",
  "borderRadius": "{{appsmith.theme.borderRadius.appBorderRadius}}",
  "borderWidth": "1",
  "bottomRow": 73,
  "boxShadow": "{{appsmith.theme.boxShadow.appBoxShadow}}",
  "canFreezeColumn": true,
  "childStylesheet": {
    "button": {
      "borderRadius": "{{appsmith.theme.borderRadius.appBorderRadius}}",
      "boxShadow": "none",
      "buttonColor": "{{appsmith.theme.colors.primaryColor}}"
    },
    "editActions": {
      "discardBorderRadius": "{{appsmith.theme.borderRadius.appBorderRadius}}",
      "discardButtonColor": "{{appsmith.theme.colors.primaryColor}}",
      "saveBorderRadius": "{{appsmith.theme.borderRadius.appBorderRadius}}",
      "saveButtonColor": "{{appsmith.theme.colors.primaryColor}}"
    },
    "iconButton": {
      "borderRadius": "{{appsmith.theme.borderRadius.appBorderRadius}}",
      "boxShadow": "none",
      "buttonColor": "{{appsmith.theme.colors.primaryColor}}"
    },
    "menuButton": {
      "borderRadius": "{{appsmith.theme.borderRadius.appBorderRadius}}",
      "boxShadow": "none",
      "menuColor": "{{appsmith.theme.colors.primaryColor}}"
    }
  },
  "columnOrder": [
    "phone",
    "rowIndex"
  ],
  "columnUpdatedAt": 1750681674589,
  "columnWidthMap": {},
  "customIsLoading": false,
  "customIsLoadingValue": "",
  "defaultPageSize": 0,
  "defaultSelectedRowIndex": 0,
  "defaultSelectedRowIndices": [
    0
  ],
  "delimiter": ",",
  "dynamicBindingPathList": [
    {
      "key": "accentColor"
    },
    {
      "key": "borderRadius"
    },
    {
      "key": "boxShadow"
    },
    {
      "key": "primaryColumns.phone.computedValue"
    },
    {
      "key": "tableData"
    },
    {
      "key": "primaryColumns.rowIndex.computedValue"
    }
  ],
  "dynamicPropertyPathList": [],
  "dynamicTriggerPathList": [],
  "enableClientSideSearch": true,
  "flexVerticalAlignment": "start",
  "horizontalAlignment": "LEFT",
  "inlineEditingSaveOption": "ROW_LEVEL",
  "isLoading": false,
  "isSortable": true,
  "isVisible": true,
  "isVisibleDownload": true,
  "isVisibleFilters": false,
  "isVisiblePagination": true,
  "isVisibleSearch": true,
  "key": "lhcpf063oi",
  "label": "Data",
  "leftColumn": 0,
  "minWidth": 450,
  "mobileBottomRow": 34,
  "mobileLeftColumn": 0,
  "mobileRightColumn": 13,
  "mobileTopRow": 6,
  "needsErrorInfo": false,
  "parentColumnSpace": 19.5,
  "parentId": "v61s6uo9qi",
  "parentRowSpace": 10,
  "primaryColumns": {
    "phone": {
      "alias": "phone",
      "allowCellWrapping": false,
      "allowSameOptionsInNewRow": true,
      "cellBackground": "",
      "columnType": "number",
      "computedValue": "{{csvView.processedTableData.map((currentRow, currentIndex) => ( currentRow[\"phone\"]))}}",
      "currencyCode": "USD",
      "decimals": 0,
      "enableFilter": true,
      "enableSort": true,
      "fontStyle": "",
      "horizontalAlignment": "LEFT",
      "id": "phone",
      "index": 5,
      "isCellEditable": false,
      "isCellVisible": true,
      "isDerived": false,
      "isDisabled": false,
      "isDiscardVisible": true,
      "isEditable": false,
      "isSaveVisible": true,
      "isVisible": true,
      "label": "phone",
      "notation": "standard",
      "originalId": "phone",
      "sticky": "",
      "textColor": "",
      "textSize": "0.875rem",
      "thousandSeparator": true,
      "validation": {},
      "verticalAlignment": "CENTER",
      "width": 150
    },
    "rowIndex": {
      "alias": "rowIndex",
      "allowCellWrapping": false,
      "allowSameOptionsInNewRow": true,
      "cellBackground": "",
      "columnType": "number",
      "computedValue": "{{csvView.processedTableData.map((currentRow, currentIndex) => ( currentRow[\"rowIndex\"]))}}",
      "currencyCode": "USD",
      "decimals": 0,
      "enableFilter": true,
      "enableSort": true,
      "fontStyle": "",
      "horizontalAlignment": "LEFT",
      "id": "rowIndex",
      "index": 1,
      "isCellEditable": false,
      "isCellVisible": true,
      "isDerived": false,
      "isDisabled": false,
      "isDiscardVisible": true,
      "isEditable": false,
      "isSaveVisible": true,
      "isVisible": true,
      "label": "rowIndex",
      "notation": "standard",
      "originalId": "rowIndex",
      "sticky": "",
      "textColor": "",
      "textSize": "0.875rem",
      "thousandSeparator": true,
      "validation": {},
      "verticalAlignment": "CENTER",
      "width": 150
    }
  },
  "renderMode": "CANVAS",
  "responsiveBehavior": "fill",
  "rightColumn": 63,
  "searchKey": "",
  "tableData": "{{Find_Data1.data}}",
  "textSize": "0.875rem",
  "topRow": 8,
  "totalRecordsCount": 0,
  "type": "TABLE_WIDGET_V2",
  "version": 2,
  "verticalAlignment": "CENTER",
  "widgetId": "eio6docckw",
  "widgetName": "csvView"
}