{
  "animateLoading": true,
  "borderRadius": "{{appsmith.theme.borderRadius.appBorderRadius}}",
  "bottomRow": 5,
  "boxShadow": "none",
  "buttonColor": "{{appsmith.theme.colors.primaryColor}}",
  "buttonVariant": "TERTIARY",
  "dynamicBindingPathList": [
    {
      "key": "buttonColor"
    },
    {
      "key": "borderRadius"
    }
  ],
  "dynamicPropertyPathList": [],
  "dynamicTriggerPathList": [],
  "iconName": "user",
  "isDisabled": false,
  "isLoading": false,
  "isVisible": true,
  "key": "dkp98wgtpl",
  "leftColumn": 49,
  "minWidth": 50,
  "mobileBottomRow": 4,
  "mobileLeftColumn": 46,
  "mobileRightColumn": 50,
  "mobileTopRow": 0,
  "needsErrorInfo": false,
  "parentColumnSpace": 17.625,
  "parentId": "us7mi726xi",
  "parentRowSpace": 10,
  "renderMode": "CANVAS",
  "responsiveBehavior": "hug",
  "rightColumn": 51,
  "topRow": 1,
  "type": "ICON_BUTTON_WIDGET",
  "version": 1,
  "widgetId": "ewjglyn5qq",
  "widgetName": "userNameIcon"
}