{
  "gitSyncId": "67a78c88af45f24f85e95b40_50ce3ef0-8fb2-4508-bad0-df6f90cb401e",
  "id": "Admin Settings_logInQuery",
  "pluginId": "postgres-plugin",
  "pluginType": "DB",
  "unpublishedAction": {
    "actionConfiguration": {
      "body": "SELECT u.id, u.user_name, u.user_email \nFROM business_team_users u\nJOIN user_auth a ON u.id = a.user_id\nWHERE u.user_email = {{inputUserEmail.text}} \nAND a.password_hash = SHA2({{inputPassword.text}}, 256);",
      "encodeParamsToggle": true,
      "paginationType": "NONE",
      "pluginSpecifiedTemplates": [
        {
          "value": true
        }
      ],
      "timeoutInMillisecond": 10000
    },
    "confirmBeforeExecute": false,
    "datasource": {
      "id": "hermes-write-db-prod",
      "isAutoGenerated": false,
      "name": "hermes-write-db-prod",
      "pluginId": "postgres-plugin"
    },
    "dynamicBindingPathList": [
      {
        "key": "body"
      }
    ],
    "executeOnLoad": false,
    "name": "logInQuery",
    "pageId": "Admin Settings",
    "userSetOnLoad": false
  }
}