{
  "gitSyncId": "67a78c88af45f24f85e95b40_42fb8b40-1e52-40b4-9625-50eadc97510b",
  "id": "Dashboard_JSObject1.onResetClick",
  "pluginId": "js-plugin",
  "pluginType": "JS",
  "unpublishedAction": {
    "actionConfiguration": {
      "encodeParamsToggle": true,
      "jsArguments": [],
      "paginationType": "NONE",
      "timeoutInMillisecond": 10000
    },
    "collectionId": "Dashboard_JSObject1",
    "confirmBeforeExecute": false,
    "datasource": {
      "isAutoGenerated": false,
      "name": "UNUSED_DATASOURCE",
      "pluginId": "js-plugin"
    },
    "dynamicBindingPathList": [
      {
        "key": "body"
      }
    ],
    "executeOnLoad": false,
    "fullyQualifiedName": "JSObject1.onResetClick",
    "name": "onResetClick",
    "pageId": "Dashboard",
    "userSetOnLoad": false
  }
}