{
  "gitSyncId": "67a78c88af45f24f85e95b40_3169609c-62cb-4062-88eb-e12130e49917",
  "id": "New Leads_buttonValidation.buttonSubmitonClick",
  "pluginId": "js-plugin",
  "pluginType": "JS",
  "unpublishedAction": {
    "actionConfiguration": {
      "encodeParamsToggle": true,
      "jsArguments": [],
      "paginationType": "NONE",
      "timeoutInMillisecond": 10000
    },
    "collectionId": "New Leads_buttonValidation",
    "confirmBeforeExecute": false,
    "datasource": {
      "isAutoGenerated": false,
      "name": "UNUSED_DATASOURCE",
      "pluginId": "js-plugin"
    },
    "dynamicBindingPathList": [
      {
        "key": "body"
      }
    ],
    "executeOnLoad": false,
    "fullyQualifiedName": "buttonValidation.buttonSubmitonClick",
    "name": "buttonSubmitonClick",
    "pageId": "New Leads",
    "userSetOnLoad": false
  }
}